MANIFEST.in
README.md
requirements.txt
setup.py
django_domande.egg-info/PKG-INFO
django_domande.egg-info/SOURCES.txt
django_domande.egg-info/dependency_links.txt
django_domande.egg-info/requires.txt
django_domande.egg-info/top_level.txt
domande/__init__.py
domande/__init__.pyc
domande/admin.py
domande/forms.py
domande/forms.pyc
domande/models.py
domande/models.pyc
domande/settings.py
domande/urls.py
domande/views.py
domande/migrations/0001_initial.py
domande/migrations/__init__.py
domande/migrations/__init__.pyc