Metadata-Version: 1.1
Name: django-domande
Version: 0.1.4
Summary: django app to represent generic questions on forms
Home-page: https://github.com/bulkan/django-domande
Author: Bulkan Evcimen
Author-email: bulkan@gmail.com
License: UNKNOWN
Platform: UNKNOWN
Classifier: Development Status :: 5 - Production/Stable
Classifier: Intended Audience :: Developers
Classifier: Natural Language :: English
Classifier: Programming Language :: Python
Classifier: Programming Language :: Python :: 2.6
Classifier: Programming Language :: Python :: 2.7
